dparo/__init__.py
dparo/dparo.py
dparo-0.1.dist-info/METADATA
dparo-0.1.dist-info/WHEEL
dparo-0.1.dist-info/top_level.txt
dparo-0.1.dist-info/RECORD
