Metadata-Version: 2.1
Name: dparo
Version: 0.1
Requires-Dist: pyperclip
